ar_sync/__init__.py
ar_sync/__version__.py
ar_sync/cli.py
ar_sync/config_manager.py
ar_sync/errors.py
ar_sync/git_backend.py
ar_sync/models.py
ar_sync/project_manager.py
ar_sync/store_manager.py
ar_sync-0.1.5.dist-info/METADATA
ar_sync-0.1.5.dist-info/WHEEL
ar_sync-0.1.5.dist-info/entry_points.txt
ar_sync-0.1.5.dist-info/top_level.txt
ar_sync-0.1.5.dist-info/RECORD
