Metadata-Version: 2.4
Name: ar-sync
Version: 0.1.5
Summary: AI IDE configuration file synchronization CLI tool
Author: ar-sync contributors
License: MIT
Project-URL: Homepage, https://github.com/JINWOO-J/ar-sync
Project-URL: Repository, https://github.com/JINWOO-J/ar-sync
Project-URL: Issues, https://github.com/JINWOO-J/ar-sync/issues
Keywords: cli,sync,ai,ide,settings
Classifier: Development Status :: 3 - Alpha
Classifier: Intended Audience :: Developers
Classifier: License :: OSI Approved :: MIT License
Classifier: Programming Language :: Python :: 3
Classifier: Programming Language :: Python :: 3.10
Classifier: Programming Language :: Python :: 3.11
Classifier: Programming Language :: Python :: 3.12
Requires-Python: >=3.10
Requires-Dist: typer>=0.9.0
Requires-Dist: gitpython>=3.1.40
Requires-Dist: pyyaml>=6.0.1
Provides-Extra: dev
Requires-Dist: pytest>=7.4.0; extra == "dev"
Requires-Dist: pytest-cov>=4.1.0; extra == "dev"
Requires-Dist: hypothesis>=6.92.0; extra == "dev"
Requires-Dist: mypy>=1.7.0; extra == "dev"
Requires-Dist: types-PyYAML>=6.0.12; extra == "dev"
Requires-Dist: ruff>=0.1.0; extra == "dev"
Requires-Dist: build>=1.0.0; extra == "dev"
Requires-Dist: twine>=4.0.0; extra == "dev"
